german_snippets_data/__init__.py
german_snippets_data/main.py
german_snippets_data-0.1.0.dist-info/METADATA
german_snippets_data-0.1.0.dist-info/WHEEL
german_snippets_data-0.1.0.dist-info/entry_points.txt
german_snippets_data-0.1.0.dist-info/RECORD
