Metadata-Version: 2.4
Name: german-snippets-data
Version: 0.1.0
Summary: Add your description here
Requires-Python: >=3.9
Requires-Dist: polars>=1.33.0
